asterisk_exporter/__init__.py
asterisk_exporter/app.py
asterisk_exporter/exporter.py
asterisk_exporter/log.py
asterisk_exporter-0.0.7.dist-info/LICENSE
asterisk_exporter-0.0.7.dist-info/METADATA
asterisk_exporter-0.0.7.dist-info/WHEEL
asterisk_exporter-0.0.7.dist-info/entry_points.txt
asterisk_exporter-0.0.7.dist-info/top_level.txt
asterisk_exporter-0.0.7.dist-info/RECORD
